selecto/__init__.py
selecto/selecto.py
selecto-1.0.5.dist-info/METADATA
selecto-1.0.5.dist-info/WHEEL
selecto-1.0.5.dist-info/top_level.txt
selecto-1.0.5.dist-info/RECORD
