Metadata-Version: 2.2
Name: selecto
Version: 1.0.5
Summary: Simple, colorful, multi-mode TUI that requires no boilerplate
Home-page: https://github.com/manuel/selecto
Author: Manuel Germanos
Author-email: manuel@example.com
License: MIT
